uinspect.cpython-38-x86_64-linux-gnu.so
uinspect-0.0.5.dist-info/WHEEL
uinspect-0.0.5.dist-info/top_level.txt
uinspect-0.0.5.dist-info/RECORD
uinspect-0.0.5.dist-info/METADATA
