Metadata-Version: 2.1
Name: uinspect
Version: 0.0.5
Summary: Ultra-fast inspect functions for Python
Home-page: https://github.com/Kuree/uinspect
Author: Keyi Zhang
Author-email: keyi@cs.stanford.edu
Requires-Python: >=3.8
Provides-Extra: test
Requires-Dist: pytest (>=6.0) ; extra == 'test'
